uv_shell_hook/__init__.py
uv_shell_hook/cli.py
uv_shell_hook/py.typed
uv_shell_hook/version.py
uv_shell_hook/scripts/bash.sh
uv_shell_hook/scripts/cmd.cmd
uv_shell_hook/scripts/fish.fish
uv_shell_hook/scripts/powershell.ps1
uv_shell_hook-0.1.7.dist-info/METADATA
uv_shell_hook-0.1.7.dist-info/WHEEL
uv_shell_hook-0.1.7.dist-info/entry_points.txt
uv_shell_hook-0.1.7.dist-info/licenses/LICENSE
uv_shell_hook-0.1.7.dist-info/RECORD
