Metadata-Version: 2.4
Name: uv-shell-hook
Version: 0.1.7
Summary: This package provides a shell hook for uv allowing activating and deactivating virtual environments.
Author-email: Dheepak Krishnamurthy <1813121+kdheepak@users.noreply.github.com>
License-File: LICENSE
Requires-Python: >=3.13
Requires-Dist: rich>=14.1.0
Requires-Dist: typer>=0.16.0
